adafruit_rgbled.py
adafruit_circuitpython_rgbled-1.2.5.dist-info/licenses/LICENSE
adafruit_circuitpython_rgbled-1.2.5.dist-info/METADATA
adafruit_circuitpython_rgbled-1.2.5.dist-info/WHEEL
adafruit_circuitpython_rgbled-1.2.5.dist-info/top_level.txt
adafruit_circuitpython_rgbled-1.2.5.dist-info/RECORD
