Metadata-Version: 2.4
Name: adafruit-circuitpython-rgbled
Version: 1.2.5
Summary: CircuitPython driver for RGB LEDs
Author-email: Adafruit Industries <circuitpython@adafruit.com>
License: MIT
Project-URL: Homepage, https://github.com/adafruit/Adafruit_CircuitPython_RGBLED
Keywords: adafruit,blinka,circuitpython,micropython,rgbled,rgb,,led,,driver,,pwm
Classifier: Intended Audience :: Developers
Classifier: Topic :: Software Development :: Libraries
Classifier: Topic :: Software Development :: Embedded Systems
Classifier: Topic :: System :: Hardware
Classifier: License :: OSI Approved :: MIT License
Classifier: Programming Language :: Python :: 3
License-File: LICENSE
Requires-Dist: Adafruit-Blinka
Requires-Dist: adafruit-circuitpython-typing~=1.4
Requires-Dist: adafruit-circuitpython-pca9685
Provides-Extra: optional
Dynamic: license-file
